revns/__init__.py
revns/django.py
revns/exceptions.py
revns/py.typed
revns-2.0.4.dist-info/WHEEL
revns-2.0.4.dist-info/METADATA
revns-2.0.4.dist-info/RECORD
